<?xml version="1.0"?>
<messaging-emoticon-map >


<emoticon file="">
</emoticon>
<emoticon file="amaze">
	<string>:amaze:</string>
</emoticon>
<emoticon file="dither">
</emoticon>
<emoticon file="envy">
</emoticon>
<emoticon file="flabbergast">
	<string>:baffle:</string>
	<string>:flabbergast:</string>
</emoticon>
<emoticon file="panic">
	<string>:-s</string>
	<string>:panic:</string>
</emoticon>
<emoticon file="repulse">
</emoticon>
<emoticon file="simper">
</emoticon>
<emoticon file="smile">
	<string>:)</string>
	<string>:-)</string>
</emoticon>
<emoticon file="smirk">
</emoticon>

</messaging-emoticon-map>
